{
"companyName": "Sectordub",
"productName": "Pikuniku",
"productVersion": "1.1",
"dataUrl": "https://pub-e23e933511954d6b800894eb915b67c3.r2.dev/pikubog.data.unityweb",
"wasmCodeUrl": "pikubog.wasm.code.unityweb",
"wasmFrameworkUrl": "pikubog.wasm.framework.unityweb",
"graphicsAPI": ["WebGL 2.0","WebGL 1.0"],
"webglContextAttributes": {"preserveDrawingBuffer": false},
"splashScreenStyle": "Dark",
"backgroundColor": "#121E1E",
"developmentBuild": false,
"multithreading": false,
"unityVersion": "2019.4.29f1"
}